<?xml version='1.0' encoding='utf-8' standalone='yes' ?>
<carrier_config_list>
    <!--RIL_IN 405870 -->
    <carrier_config>
        <!-- Volte UI -->
        <string name="carrier_volte_hd_icon_flag">10101010</string>
        <!--UT TA -->
        <boolean name="utForbiddenWhenVolteSwitchOff" value="false" />
        <int name="utNafPort" value="7077" />
        <string name="utBsfSrvAddr">bsf.ims.mnc870.mcc405.pub.3gppnetwork.org</string>
        <int name="utBsfPort" value="7080" />
        <!--VOLTE TA -->
        <boolean name="carrier_default_volte_switch_on_bool" value="true" />
        <!-- VOWIFI NO TA -->
        <string name="vowifiHplmnListItem">405870, vowifi.jio.com</string>
        <string name="Ikev2EncAlg">RCT_ALG_DES3_CBC,RCT_ALG_AES128_CBC,RCT_ALG_AES192_CBC,RCT_ALG_AES256_CBC</string>
        <string name="Ikev2PrfAlg">RCT_ALG_HMAC_MD5,RCT_ALG_HMAC_SHA1,RCT_ALG_AES_XCBC</string>
        <string name="Ikev2HashAlg">RCT_ALG_HMAC_MD5,RCT_ALG_HMAC_SHA1,RCT_ALG_AES_XCBC</string>
        <string name="Ikev2DhGroup">RCT_ALG_MODP1024,RCT_ALG_MODP1536,RCT_ALG_MODP2048</string>
        <string name="EspEncAlg">RCT_ALG_DES3_CBC,RCT_ALG_AES128_CBC,RCT_ALG_AES192_CBC,RCT_ALG_AES256_CBC</string>
        <string name="EspAuthAlg">RCT_ALG_HMAC_MD5,RCT_ALG_HMAC_SHA1,RCT_ALG_AES_XCBC</string>
        <boolean name="vowifi_roaming_switch" value="true"/>
        <boolean name="vowifi_ut_switch" value="true"/>
        <int name="Ikev2IkeSaRekeyTimerSec" value="86400" />
        <int name="Ikev2IPsecSaRekeyTimeSec" value="86400" />
        <int name="Ikev2MaxRetryToSend" value="3"/>
        <int name="vowifiRoamingConfig" value="0"/>
        <boolean name="vowifiStaticUnroaming" value="true"/>
        <boolean name="vowifiStaticRoaming" value="true"/>
    </carrier_config>
</carrier_config_list>
